brie_commit/__init__.py
brie_commit/gouda.py
brie_commit-1.1.0.dist-info/entry_points.txt
brie_commit-1.1.0.dist-info/LICENSE
brie_commit-1.1.0.dist-info/METADATA
brie_commit-1.1.0.dist-info/WHEEL
brie_commit-1.1.0.dist-info/RECORD
